BubbleNova/BubbleNova.py
BubbleNova/__init__.py
BubbleNova-0.0.5.dist-info/LICENSE
BubbleNova-0.0.5.dist-info/METADATA
BubbleNova-0.0.5.dist-info/WHEEL
BubbleNova-0.0.5.dist-info/top_level.txt
BubbleNova-0.0.5.dist-info/RECORD
