Metadata-Version: 2.1
Name: BubbleNova
Version: 0.0.5
Summary: A Python library for running multiple Discord bots at once.
Home-page: UNKNOWN
Author: SoapDoesCode
Author-email: 
License: UNKNOWN
Keywords: python,discord,disord bot,bubble nova
Platform: UNKNOWN
Classifier: Development Status :: 1 - Planning
Classifier: Intended Audience :: Developers
Classifier: Programming Language :: Python :: 3
Classifier: Operating System :: Unix
Classifier: Operating System :: MacOS :: MacOS X
Classifier: Operating System :: Microsoft :: Windows
License-File: LICENSE
